examples/append_from_local.py
examples/check_setup.py
examples/download_export.py
examples/upload_and_share_cli.py
examples/upload_from_s3.py
gigasheet/__init__.py
gigasheet/gigasheet.py
gigasheet/test_gigasheet.py
gigasheet/testdata/sample-local-upload.csv
gigasheet-2.3.0.dist-info/LICENSE
gigasheet-2.3.0.dist-info/METADATA
gigasheet-2.3.0.dist-info/WHEEL
gigasheet-2.3.0.dist-info/RECORD
