Metadata-Version: 2.1
Name: gigasheet
Version: 2.3.0
Summary: Gigasheet Python SDK
Home-page: https://www.gigasheet.com
License: MIT
Author: Gigasheet
Author-email: support@gigasheet.com
Requires-Python: >=3.8.1,<4.0
Classifier: License :: OSI Approved :: MIT License
Classifier: Programming Language :: Python :: 3
Classifier: Programming Language :: Python :: 3.9
Classifier: Programming Language :: Python :: 3.10
Classifier: Programming Language :: Python :: 3.11
Classifier: Programming Language :: Python :: 3.12
Classifier: Programming Language :: Python :: 3.13
Requires-Dist: requests (>=2,<3)
Project-URL: Documentation, https://gigasheet.readme.io/
Project-URL: Repository, https://github.com/gigasheetco/gigasheet-python
